{
	"info": {
		"_postman_id": "9ec63d7a-d7b8-4cd6-9191-fa54cca5f629",
		"name": "Desafio1",
		"schema": "https://schema.getpostman.com/json/collection/v2.1.0/collection.json"
	},
	"item": [
		{
			"name": "1- follow",
			"request": {
				"method": "POST",
				"header": [],
				"url": {
					"raw": "localhost:8080/users/2/follow/0",
					"host": [
						"localhost"
					],
					"port": "8080",
					"path": [
						"users",
						"2",
						"follow",
						"0"
					]
				}
			},
			"response": []
		},
		{
			"name": "2- count followers",
			"request": {
				"method": "GET",
				"header": [],
				"url": {
					"raw": "localhost:8080/users/2/followers/count/",
					"host": [
						"localhost"
					],
					"port": "8080",
					"path": [
						"users",
						"2",
						"followers",
						"count",
						""
					]
				}
			},
			"response": []
		},
		{
			"name": "3- list followers",
			"request": {
				"method": "GET",
				"header": [],
				"url": {
					"raw": "localhost:8080/users/4/followers/list?order=name_asc",
					"host": [
						"localhost"
					],
					"port": "8080",
					"path": [
						"users",
						"4",
						"followers",
						"list"
					],
					"query": [
						{
							"key": "order",
							"value": "name_asc"
						}
					]
				}
			},
			"response": []
		},
		{
			"name": "4- list followed",
			"request": {
				"method": "GET",
				"header": [],
				"url": {
					"raw": "localhost:8080/users/1/followed/list?order=name_asc",
					"host": [
						"localhost"
					],
					"port": "8080",
					"path": [
						"users",
						"1",
						"followed",
						"list"
					],
					"query": [
						{
							"key": "order",
							"value": "name_asc"
						}
					]
				}
			},
			"response": []
		},
		{
			"name": "5- create post1",
			"request": {
				"method": "POST",
				"header": [],
				"body": {
					"mode": "raw",
					"raw": "{\n    \"userId\": 0,\n    \"postId\": 1,\n    \"date\": \"08-06-2021\",\n    \"detail\":\n    {\n        \"productId\": 1,\n        \"productName\": \"Silla Gamer\",\n        \"type\": \"Gamer\",\n        \"brand\": \"Racer\",\n        \"color\": \"Red & Black\",\n        \"notes\": \"Special Edition\"\n    },\n    \"category\": 100,\n    \"price\": 1500.50\n}",
					"options": {
						"raw": {
							"language": "json"
						}
					}
				},
				"url": {
					"raw": "localhost:8080/products/newpost",
					"host": [
						"localhost"
					],
					"port": "8080",
					"path": [
						"products",
						"newpost"
					]
				}
			},
			"response": []
		},
		{
			"name": "5-  create post2",
			"request": {
				"method": "POST",
				"header": [],
				"body": {
					"mode": "raw",
					"raw": "{\n    \"userId\": 0,\n    \"postId\": 2,\n    \"date\": \"10-04-2021\",\n    \"detail\":\n    {\n        \"productId\": 2,\n        \"productName\": \"Mouse Gamer\",\n        \"type\": \"Gamer\",\n        \"brand\": \"Racer2\",\n        \"color\": \"Red & Green\",\n        \"notes\": \"Standart\"\n    },\n    \"category\": 200,\n    \"price\": 3000.10\n}",
					"options": {
						"raw": {
							"language": "json"
						}
					}
				},
				"url": {
					"raw": "localhost:8080/products/newpost",
					"host": [
						"localhost"
					],
					"port": "8080",
					"path": [
						"products",
						"newpost"
					]
				}
			},
			"response": []
		},
		{
			"name": "5-  create post3",
			"request": {
				"method": "POST",
				"header": [],
				"body": {
					"mode": "raw",
					"raw": "{\n    \"userId\": 0,\n    \"postId\": 3,\n    \"date\": \"30-05-2021\",\n    \"detail\":\n    {\n        \"productId\": 33,\n        \"productName\": \"Mesa\",\n        \"type\": \"Gamer\",\n        \"brand\": \"Racer3\",\n        \"color\": \"Red & Green\",\n        \"notes\": \"Standart3\"\n    },\n    \"category\": 300,\n    \"price\": 4000.10\n}",
					"options": {
						"raw": {
							"language": "json"
						}
					}
				},
				"url": {
					"raw": "localhost:8080/products/newpost",
					"host": [
						"localhost"
					],
					"port": "8080",
					"path": [
						"products",
						"newpost"
					]
				}
			},
			"response": []
		},
		{
			"name": "5-  create post4",
			"request": {
				"method": "POST",
				"header": [],
				"body": {
					"mode": "raw",
					"raw": "{\n    \"userId\": 0,\n    \"postId\": 4,\n    \"date\": \"28-05-2021\",\n    \"detail\":\n    {\n        \"productId\": 55,\n        \"productName\": \"Teclado Gamer\",\n        \"type\": \"Gamer\",\n        \"brand\": \"Racer\",\n        \"color\": \"Red & Black\",\n        \"notes\": \"Special Edition\"\n    },\n    \"category\": 100,\n    \"price\": 1500.50\n}",
					"options": {
						"raw": {
							"language": "json"
						}
					}
				},
				"url": {
					"raw": "localhost:8080/products/newpost",
					"host": [
						"localhost"
					],
					"port": "8080",
					"path": [
						"products",
						"newpost"
					]
				}
			},
			"response": []
		},
		{
			"name": "6-  post list followed",
			"request": {
				"method": "GET",
				"header": [],
				"url": null
			},
			"response": []
		},
		{
			"name": "7- unfollow",
			"request": {
				"method": "POST",
				"header": [],
				"url": {
					"raw": "localhost:8080/users/2/unfollow/0",
					"host": [
						"localhost"
					],
					"port": "8080",
					"path": [
						"users",
						"2",
						"unfollow",
						"0"
					]
				}
			},
			"response": []
		},
		{
			"name": "10- create promopost1",
			"request": {
				"method": "POST",
				"header": [],
				"body": {
					"mode": "raw",
					"raw": "{\n    \"userId\": 0,\n    \"postId\": 10,\n    \"date\": \"29-05-2021\",\n    \"detail\":\n    {\n        \"productId\": 41,\n        \"productName\": \"Escritorio Gamer\",\n        \"type\": \"Gamer\",\n        \"brand\": \"Racer3\",\n        \"color\": \"Red & Green\",\n        \"notes\": \"Standart3\"\n    },\n    \"category\": 300,\n    \"price\": 5560.10,\n    \"hasPromo\": true,\n    \"discount\": 0.25\n}",
					"options": {
						"raw": {
							"language": "json"
						}
					}
				},
				"url": {
					"raw": "localhost:8080/products/newpromopost",
					"host": [
						"localhost"
					],
					"port": "8080",
					"path": [
						"products",
						"newpromopost"
					]
				}
			},
			"response": []
		},
		{
			"name": "10- create promopost2",
			"request": {
				"method": "POST",
				"header": [],
				"body": {
					"mode": "raw",
					"raw": "{\n    \"userId\": 0,\n    \"postId\": 28,\n    \"date\": \"26-05-2021\",\n    \"detail\":\n    {\n        \"productId\": 43,\n        \"productName\": \"Armario\",\n        \"type\": \"Normal\",\n        \"brand\": \"Racer55\",\n        \"color\": \"Red & White\",\n        \"notes\": \"Standart123\"\n    },\n    \"category\": 3100,\n    \"price\": 41000.10,\n    \"hasPromo\": true,\n    \"discount\": 0.35\n}",
					"options": {
						"raw": {
							"language": "json"
						}
					}
				},
				"url": {
					"raw": "localhost:8080/products/newpromopost",
					"host": [
						"localhost"
					],
					"port": "8080",
					"path": [
						"products",
						"newpromopost"
					]
				}
			},
			"response": []
		},
		{
			"name": "11- count promo post seller",
			"request": {
				"method": "GET",
				"header": [],
				"url": {
					"raw": "localhost:8080/products/0/countPromo",
					"host": [
						"localhost"
					],
					"port": "8080",
					"path": [
						"products",
						"0",
						"countPromo"
					]
				}
			},
			"response": []
		},
		{
			"name": "12- list promopost seller",
			"request": {
				"method": "GET",
				"header": [],
				"url": {
					"raw": "localhost:8080/products/0/list?order=name_desc",
					"host": [
						"localhost"
					],
					"port": "8080",
					"path": [
						"products",
						"0",
						"list"
					],
					"query": [
						{
							"key": "order",
							"value": "name_desc"
						}
					]
				}
			},
			"response": []
		}
	]
}